pyfreya/__init__.py
pyfreya/pyfreya.py
pyfreya/cohort/__init__.py
pyfreya/cohort/cohort.py
pyfreya/retention/__init__.py
pyfreya/retention/fit_functions.py
pyfreya/retention/retention.py
pyfreya/revenue/__init__.py
pyfreya/revenue/revenue.py
pyfreya-0.3.0.dist-info/AUTHORS.rst
pyfreya-0.3.0.dist-info/LICENSE
pyfreya-0.3.0.dist-info/METADATA
pyfreya-0.3.0.dist-info/WHEEL
pyfreya-0.3.0.dist-info/top_level.txt
pyfreya-0.3.0.dist-info/RECORD
